{"9EQ0amnSqdXG0+0dTrYw8A==":"dg-logo.png","7/V3VhaEfF1Qy6NsPuup8A==":"dg-logo-1.png","HTBKikBBkF9ox4QeQg3NoA==":"dg-logo-2.png","prYE2iqcDbDt0tXcvDevdA==":"dg-logo-3.png","Y8U1cOad4gIXJ/yocmCX2A==":"wallpaper-bg.png","1pNeoohS6cJpEDBoV7JOLg==":"wallpaper-bg-1.png","E4m9i4WfCV8pGztaP/M2AQ==":"bladee-member.jpg","9ua4XOGH3hsh6WhwFOfOMA==":"bladee-member.jpeg","Z2fc4HveiNNUfH8vbftfGg==":"thaiboi-member-copy.jpeg","BBi0njZNn7e7ZnJpAhxYkw==":"ecco2k-member.jpeg","WDvTON1aH55gRL/LQWvJSA==":"ecco2k-member-1.jpeg","MI6Ku08HUjOEwQeueU13OQ==":"whitearmor.png","KN+dsQzDLHxAByq+fFZSFA==":"icedancer.jpg","vNRabqFlQXBgkiW6F0ipuQ==":"333.png","+ocNvvamyr7OYNYwn3TbRw==":"the-fool.png","i9IvYj8iOuIM/yNadfPs9w==":"spider.png","TSQpPyCKLxd3JV4Ze5sK7Q==":"legendary.jpg","2tjvW9kV08o57Bmm6uPnYw==":"yin-yang.jpg","167UFPzTZhvrpAcGKmvwyw==":"ecco2k.jpg","gwqeckeHKEirdKS8cYFGfw==":"back-2-life.jpg","nxsxqRvZDJcVWZUfiBsMcw==":"e.png","ypOlULxNtShVRSN+C5cDtA==":"dgggg.jpg","QkB8pRGdi7AMRKRWoC5zug==":"crest.jpg","t2x7NDeW7QhX9edehRMhZQ==":"red-light.jpg","DPjD2pB7APM+TJ1wQcX4Gw==":"primavera.png","wusb3wJWM8CO0+WoselMjQ==":"gang.png","crxPyMsgFMyWLZ/ISTwjJA==":"primavera-2.png","qoHw6IyiIDSBtGnH9Dv0qA==":"dg-1.png","Uv1PQEldhbpnqjfEDSqknw==":"dg-2.jpg","BlRH3o7EAxOsTrsR3proZg==":"dg-3.jpg","tAkWXzFVY9mXA+gUYr5qXQ==":"dg-4.png","G4tnztHKzs2Gc+oxsRr8mg==":"dg-5.png","41ZPASCN1URz6b9cFjx1KQ==":"wallpaper-bg-copy.png","enC2KT9LTrZYbxbdJJliUg==":"wallpaper-bg-copy-min.png","pPx2O9tjK/Mw1wn4MqHUnA==":"bladee-member-1.jpeg","Laf1iwE/JtFbpedFW78nsQ==":"thaiboi-member-copy-1.jpeg","6a28HD4RAbJ1Y38OEzMD7g==":"thaiboi-member-copy-2.jpeg","eqUaFsS4Dd8Wi9AK2UlvBA==":"ecco2k-member-2.jpeg","GTNI9Sd4nQVx+4VK6qfsaQ==":"boy-testimonials.jpeg","QrZwQ994XFXYuZXO16sk3A==":"girl-testimonials.jpeg","WV+HMbfRrEvBJqcwGnsPOA==":"dg-2.png","H57ELDIoBln830KC8ei7pw==":"dg-4.jpg","bOOTg9i5N5Kl45jlmbWe6A==":"dg-5.jpg","QL2/2MSPDcVsnenvI1HTrw==":"dg-6.png","Zs/205Jhh5G+ZTCMwUzoRg==":"dg-7.png","t3EJbDuGy5ZsULESl9auOA==":"bgggggggggggg.png","+Bm3k/T/1dPtmLJblVtuMA==":"bgggggggggggg-1.png","Ho/KHP3kJHLzvOErC0cH8A==":"whitearmor-1.png","6sg5ClI3Okk46Xkj2vxDsg==":"whitearmor-copy.jpg","GeEXqZCaFmHFauS4hsWEjA==":"primavera-copy.jpg","FXsBfHI497EFu3RXcfxktQ==":"gang-copy.jpg","BYBUofhKu5vvhp0YSvz29w==":"primavera-2-copy.jpg","h2asM8zc5OpvurFkwuDc8g==":"dg-1.jpg","M11cpOOOXzMMP2I4+5EB4Q==":"dg-6.jpg","QxsT0tEu1xmmXJoLgn/cLQ==":"dg-7.jpg"}